ganicas_utils/__init__.py
ganicas_utils/config.py
ganicas_utils/logging/__init__.py
ganicas_utils/logging/configuration.py
ganicas_utils/logging/formatter.py
ganicas_utils/logging/logger.py
ganicas_utils/logging/middlewares.py
ganicas_utils/logging/utils.py
ganicas_package-0.2.0.dist-info/METADATA
ganicas_package-0.2.0.dist-info/WHEEL
ganicas_package-0.2.0.dist-info/RECORD
